LICENSE
MANIFEST.in
README.md
setup.cfg
setup.py
django_maploom_registry.egg-info/PKG-INFO
django_maploom_registry.egg-info/SOURCES.txt
django_maploom_registry.egg-info/dependency_links.txt
django_maploom_registry.egg-info/not-zip-safe
django_maploom_registry.egg-info/top_level.txt
maploom_registry/__init__.py
maploom_registry/models.py
maploom_registry/tests.py
maploom_registry/geonode/__init__.py
maploom_registry/geonode/urls.py
maploom_registry/static/maploom/assets/MapLoom-1.5.0.css
maploom_registry/static/maploom/assets/MapLoom-1.5.0.js
maploom_registry/static/maploom/assets/error.png
maploom_registry/static/maploom/assets/media-default.png
maploom_registry/static/maploom/assets/media-error.png
maploom_registry/static/maploom/assets/play-pause.png
maploom_registry/static/maploom/assets/video-play.png
maploom_registry/static/maploom/fonts/glyphicons-halflings-regular.eot
maploom_registry/static/maploom/fonts/glyphicons-halflings-regular.svg
maploom_registry/static/maploom/fonts/glyphicons-halflings-regular.woff
maploom_registry/templates/maploom/_maploom_js.html
maploom_registry/templates/maploom/_maploom_map.html
maploom_registry/templates/maps/map_view.html
maploom_registry/templates/maps/maploom.html
maploom_registry/templatetags/__init__.py
maploom_registry/templatetags/maploom_tags.py